[
  {
    "contestName": "Business Plan Competition",
    "image": "https://as1.ftcdn.net/v2/jpg/03/43/43/72/1000_F_343437244_HrxIVZWbfh29tgxuRlxbPXEpHMSmfkAn.jpg",
    "description": "Submit your innovative business plan ideas. Show your strategic approach and vision.",
    "prizeMoney": 5000,
    "taskSubmissionInstructions": "Upload your business plan document in PDF format.",
    "tags": ["Business Contest"],
    "deadline": "2023-12-15",
    "status": "pending",
    "winnerID":["6562373f1e674fe582bbbc4b","6562373f1e674fe582bbbc49","6562373f1e674fe582bbbc4a"],
    "type": "Business",
    "creatorID":"",
    "participants":[]
  },
  {
    "contestName": "Medical Research Symposium",
    "image": "https://as1.ftcdn.net/v2/jpg/03/43/43/72/1000_F_343437244_HrxIVZWbfh29tgxuRlxbPXEpHMSmfkAn.jpg",
    "description": "Present groundbreaking medical research findings. Share insights and discoveries.",
    "prizeMoney": 7000,
    "taskSubmissionInstructions": "Submit an abstract and a presentation proposal.",
    "tags": ["Medical Contest"],
    "deadline": "2024-01-10",
    "status": "approved",
    "winnerID": "ObjectId5",
    "type": "Medical",
    "creatorID":"6563571e5031084f2d4ae05b",
    "participants":[
      "user1@example.com",
      "test.user2@testdomain.com",
      "another.email@gmail.com",
      "example.email@emailprovider.com",
      "my.email@customdomain.net"
    ]
  },
  {
    "contestName": "Article Writing Challenge",
    "image": "https://as1.ftcdn.net/v2/jpg/03/43/43/72/1000_F_343437244_HrxIVZWbfh29tgxuRlxbPXEpHMSmfkAn.jpg",
    "description": "Craft compelling articles on diverse topics. Showcase your writing prowess.",
    "prizeMoney": 3000,
    "taskSubmissionInstructions": "Submit your article in a Word or PDF format.",
    "tags": ["Article Writing"],
    "deadline": "2023-11-30",
    "status": "approved",
    "winnerID": ["6561ee5a1e674fe582bbbc2a","6561ee5a1e674fe582bbbc29","656233251e674fe582bbbc44"],
    "type": "Writing",
    "creatorID":"6563571e5031084f2d4ae05b",
    "participants": [
      "john.doe@example.com",
      "jane_smith@testdomain.com",
      "emailtest123@gmail.com",
      "user@emailprovider.com",
      "custom.email@customdomain.net"
    ]
  },
  {
    "contestName": "Gaming Tournament",
    "image": "https://as1.ftcdn.net/v2/jpg/03/43/43/72/1000_F_343437244_HrxIVZWbfh29tgxuRlxbPXEpHMSmfkAn.jpg",
    "description": "Compete in various gaming challenges. Test your gaming skills.",
    "prizeMoney": 2000,
    "taskSubmissionInstructions": "Join the tournament and follow the gameplay instructions.",
    "tags": ["Gaming"],
    "deadline": "2023-12-05",
    "status": "rejected",
    "winnerID": null,
    "type": "Gaming",
    "creatorID":"",
    "participants":[]
  },
  {
    "contestName": "Tech Hackathon",
    "image": "https://as1.ftcdn.net/v2/jpg/03/43/43/72/1000_F_343437244_HrxIVZWbfh29tgxuRlxbPXEpHMSmfkAn.jpg",
    "description": "Code, innovate, and build tech solutions. Work collaboratively in a hackathon environment.",
    "prizeMoney": 6000,
    "taskSubmissionInstructions": "Submit your project and code repository link.",
    "tags": ["Tech Contest"],
    "deadline": "2024-02-20",
    "status": "pending",
    "winnerID": null,
    "type": "Tech",
    "creatorID":"6563571e5031084f2d4ae05b",
    
    "participants": [
      "testuser@example.com",
      "user123@testdomain.com",
      "email.testing@gmail.com",
      "sample.email@emailprovider.com",
      "mail@customdomain.net"
    ]
  },
  {
    "contestName": "Design Challenge",
    "image": "https://as1.ftcdn.net/v2/jpg/03/43/43/72/1000_F_343437244_HrxIVZWbfh29tgxuRlxbPXEpHMSmfkAn.jpg",
    "description": "Showcase your creativity in design. Solve design problems and present visually appealing solutions.",
    "prizeMoney": 4000,
    "taskSubmissionInstructions": "Upload your design files in a compressed format.",
    "tags": ["Design Contest"],
    "deadline": "2024-03-10",
    "status": "approved",
    "winnerID": "ObjectId1",
    "type": "Design",
    "creatorID":"6563571e5031084f2d4ae05b",
    "participants":[]
  },
  {
    "contestName": "Coding Competition",
    "image": "https://as1.ftcdn.net/v2/jpg/03/43/43/72/1000_F_343437244_HrxIVZWbfh29tgxuRlxbPXEpHMSmfkAn.jpg",
    "description": "Demonstrate coding skills in various programming challenges.",
    "prizeMoney": 2500,
    "taskSubmissionInstructions": "Submit your code snippets and solutions.",
    "tags": ["Coding Contest"],
    "deadline": "2023-12-20",
    "status": "pending",
    "winnerID": null,
    "type": "Coding",
    "creatorID":"",
    "participants":[]
  },
  {
    "contestName": "Photography Contest",
    "image": "https://as1.ftcdn.net/v2/jpg/03/43/43/72/1000_F_343437244_HrxIVZWbfh29tgxuRlxbPXEpHMSmfkAn.jpg",
    "description": "Capture moments and share artistic photography.",
    "prizeMoney": 1500,
    "taskSubmissionInstructions": "Upload your high-resolution photographs.",
    "tags": ["Photography"],
    "deadline": "2024-01-05",
    "status": "approved",
    "winnerID": null,
    "type": "Photography",
    "creatorID":"",
    "participants":[]
  },
  {
    "contestName": "Music Composition Challenge",
    "image": "https://as1.ftcdn.net/v2/jpg/03/43/43/72/1000_F_343437244_HrxIVZWbfh29tgxuRlxbPXEpHMSmfkAn.jpg",
    "description": "Compose music and showcase your musical talent.",
    "prizeMoney": 3500,
    "taskSubmissionInstructions": "Submit your audio files in a compatible format.",
    "tags": ["Music Contest"],
    "deadline": "2024-02-15",
    "status": "pending",
    "winnerID": null,
    "type": "Music",
    "creatorID":"",
    "participants":[]
  },
  {
    "contestName": "Data Science Olympiad",
    "image": "https://as1.ftcdn.net/v2/jpg/03/43/43/72/1000_F_343437244_HrxIVZWbfh29tgxuRlxbPXEpHMSmfkAn.jpg",
    "description": "Solve complex data problems and showcase your data science skills.",
    "prizeMoney": 8000,
    "taskSubmissionInstructions": "Submit your data analysis report and findings.",
    "tags": ["Data Science Contest"],
    "deadline": "2024-03-01",
    "status": "pending",
    "winnerID": null,
    "type": "Data Science",
    "creatorID":"",
    "participants":[]
  }
]